requests_rest.py
pyczml-0.0.1.dist-info/METADATA
pyczml-0.0.1.dist-info/WHEEL
pyczml-0.0.1.dist-info/top_level.txt
pyczml-0.0.1.dist-info/RECORD
