Metadata-Version: 2.1
Name: pyczml
Version: 0.0.1
Summary: A czml tool.
Home-page: https://github.com/xiyusullos/pyczml
Author: aponder
Author-email: i@aponder.top
License: MIT
Platform: UNKNOWN
Classifier: License :: OSI Approved :: MIT License
Classifier: Programming Language :: Python
Classifier: Programming Language :: Python :: 3.6
Classifier: Programming Language :: Python :: Implementation :: CPython
Classifier: Programming Language :: Python :: Implementation :: PyPy
Requires-Python: >=3.6.0
